pyeasyphd/.python-version
pyeasyphd/Main.sublime-menu
pyeasyphd/__init__.py
pyeasyphd/pyeasyphd.py
pyeasyphd/pyeasyphd.sublime-settings
pyeasyphd/pyeasyphd.sublime-syntax
pyeasyphd/data/templates/csl/apa-no-ampersand.csl
pyeasyphd/data/templates/csl/apa.csl
pyeasyphd/data/templates/csl/ieee.csl
pyeasyphd/data/templates/tex/Article.tex
pyeasyphd/data/templates/tex/Article_Header.tex
pyeasyphd/data/templates/tex/Article_Tail.tex
pyeasyphd/data/templates/tex/Beamer_Header.tex
pyeasyphd/data/templates/tex/Beamer_Tail.tex
pyeasyphd/data/templates/tex/Style.tex
pyeasyphd/data/templates/tex/TEVC_Header.tex
pyeasyphd/data/templates/tex/TEVC_Tail.tex
pyeasyphd/data/templates/tex/eisvogel.tex
pyeasyphd/data/templates/tex/math.tex
pyeasyphd/data/templates/tex/math_commands.tex
pyeasyphd/data/templates/tex/nextaimathmacros.sty
pyeasyphd/main/__init__.py
pyeasyphd/main/basic_input.py
pyeasyphd/main/pandoc_md_to.py
pyeasyphd/main/python_run_md.py
pyeasyphd/main/python_run_tex.py
pyeasyphd/scripts/__init__.py
pyeasyphd/scripts/_base.py
pyeasyphd/scripts/run_article_md.py
pyeasyphd/scripts/run_article_tex.py
pyeasyphd/scripts/run_beamer_tex.py
pyeasyphd/scripts/run_compare.py
pyeasyphd/scripts/run_format.py
pyeasyphd/scripts/run_generate.py
pyeasyphd/scripts/run_replace.py
pyeasyphd/scripts/run_search.py
pyeasyphd/tools/__init__.py
pyeasyphd/tools/py_merge_tex.py
pyeasyphd/tools/py_run_bib_md_tex.py
pyeasyphd/tools/generate/generate_from_bibs.py
pyeasyphd/tools/generate/generate_html.py
pyeasyphd/tools/generate/generate_library.py
pyeasyphd/tools/generate/generate_links.py
pyeasyphd/tools/search/data.py
pyeasyphd/tools/search/search_base.py
pyeasyphd/tools/search/search_core.py
pyeasyphd/tools/search/search_keywords.py
pyeasyphd/tools/search/search_writers.py
pyeasyphd/tools/search/utils.py
pyeasyphd/utils/utils.py
pyeasyphd-0.5.0.1.dist-info/METADATA
pyeasyphd-0.5.0.1.dist-info/WHEEL
pyeasyphd-0.5.0.1.dist-info/licenses/LICENSE
pyeasyphd-0.5.0.1.dist-info/RECORD
