Metadata-Version: 2.4
Name: pyeasyphd
Version: 0.5.0.1
Summary: pyeasyphd
Project-URL: Homepage, https://github.com/Easy-PhD/pyeasyphd
Project-URL: Repository, https://github.com/Easy-PhD/pyeasyphd
Project-URL: Documentation, https://Easy-PhD.github.io/pyeasyphd
Project-URL: Source, https://github.com/Easy-PhD/pyeasyphd
Project-URL: Issues, https://github.com/Easy-PhD/pyeasyphd/issues
Project-URL: Changelog, https://github.com/Easy-PhD/pyeasyphd/releases
Author-email: NextAI <nextartifintell@gmail.com>
Maintainer-email: NextAI <nextartifintell@gmail.com>
License-Expression: GPL-3.0-or-later
License-File: LICENSE
Keywords: BibTex,Python
Classifier: Operating System :: OS Independent
Classifier: Programming Language :: Python
Classifier: Programming Language :: Python :: 3
Classifier: Programming Language :: Python :: 3.12
Classifier: Programming Language :: Python :: 3.13
Classifier: Programming Language :: Python :: 3.14
Classifier: Topic :: Software Development :: Libraries :: Python Modules
Requires-Python: >=3.12
Requires-Dist: pybibtexer>=0.3.42
